编程中经常有交换变量的操作，一般都使用中间变量，比如

```
temp = x
x = y
y = temp
```

还有一种比较pythonic的方法

```
x,y = y,x
```

简洁得多，少一个变量，写法清爽，关键是性能还高

测试一下，所谓的“不服跑个分”

```
In [1]: Timer("temp=x;x=y;y=x","x=2;y=3").timeit()
Out[1]: 0.0300906

In [2]: Timer("x,y=y,x","x=2;y=3").timeit()
Out[2]: 0.02562690000000245
```

 可以看到第二种稍快。如果使用ipython内置的%timeit测试

```
In [24]: %timeit "x=3;y=4;temp=x;x=y;y=x"
10.7 ns ± 0.177 ns per loop (mean ± std. dev. of 7 runs, 100000000 loops each)

In [25]: %timeit "x=3;y=4;x,y=y,x"
10.7 ns ± 0.0756 ns per loop (mean ± std. dev. of 7 runs, 100000000 loops each)
```

二者差不多

使用dis查看

```
In [22]: dis.dis("x,y=y,x")
  1           0 LOAD_NAME                0 (y)
              2 LOAD_NAME                1 (x)
              4 ROT_TWO
              6 STORE_NAME               1 (x)
              8 STORE_NAME               0 (y)
             10 LOAD_CONST               0 (None)
             12 RETURN_VALUE

In [23]: dis.dis("temp=x;x=y;y=x")
  1           0 LOAD_NAME                0 (x)
              2 STORE_NAME               1 (temp)
              4 LOAD_NAME                2 (y)
              6 STORE_NAME               0 (x)
              8 LOAD_NAME                0 (x)
             10 STORE_NAME               2 (y)
             12 LOAD_CONST               0 (None)
             14 RETURN_VALUE
```

第二种和第一种的区别主要是x,y=y,x方式使用ROT_TWO交换栈顶元素，比LOAD_NAME+STORE_NAME快